djangoldp_needle/__init__.py
djangoldp_needle/admin.py
djangoldp_needle/apps.py
djangoldp_needle/djangoldp_settings.py
djangoldp_needle/djangoldp_urls.py
djangoldp_needle/settings.py
djangoldp_needle/form/__init__.py
djangoldp_needle/form/needle_user_form.py
djangoldp_needle/management/__init__.py
djangoldp_needle/management/commands/__init__.py
djangoldp_needle/management/commands/importneedledata.py
djangoldp_needle/migrations/0001_initial.py
djangoldp_needle/migrations/0002_tag.py
djangoldp_needle/migrations/0003_annotation_tags.py
djangoldp_needle/migrations/0004_annotationtarget_image.py
djangoldp_needle/migrations/0005_annotationtarget_title.py
djangoldp_needle/migrations/0006_auto_20221101_1846.py
djangoldp_needle/migrations/0007_auto_20221114_1643.py
djangoldp_needle/migrations/0008_activity.py
djangoldp_needle/migrations/0009_activity_subtitle.py
djangoldp_needle/migrations/0010_activity_read.py
djangoldp_needle/migrations/0011_auto_20221125_1015.py
djangoldp_needle/migrations/0012_needleactivity_activity_type.py
djangoldp_needle/migrations/0013_needleuserprofile.py
djangoldp_needle/migrations/0014_auto_20230105_1238.py
djangoldp_needle/migrations/0015_auto_20230112_1339.py
djangoldp_needle/migrations/0016_auto_20230123_1741.py
djangoldp_needle/migrations/0017_annotationintersectionread.py
djangoldp_needle/migrations/0018_auto_20230129_1617.py
djangoldp_needle/migrations/0019_auto_20230208_1213.py
djangoldp_needle/migrations/0019_contactmessage.py
djangoldp_needle/migrations/0020_contactmessage_creation_date.py
djangoldp_needle/migrations/0021_merge_20230213_1548.py
djangoldp_needle/migrations/0022_annotation_annotation_date.py
djangoldp_needle/migrations/0023_booklet.py
djangoldp_needle/migrations/0024_auto_20230328_0814.py
djangoldp_needle/migrations/0025_needleuserfollow.py
djangoldp_needle/migrations/0026_auto_20230331_1603.py
djangoldp_needle/migrations/0027_needleuserfollow_creation_date.py
djangoldp_needle-0.1.105.dist-info/LICENSE.md
djangoldp_needle-0.1.105.dist-info/METADATA
djangoldp_needle-0.1.105.dist-info/WHEEL
djangoldp_needle-0.1.105.dist-info/top_level.txt
djangoldp_needle-0.1.105.dist-info/RECORD
