Metadata-Version: 2.1
Name: djangoldp-needle
Version: 0.1.105
Summary: Needle backend
Home-page: UNKNOWN
License: MIT
Platform: UNKNOWN
Classifier: Programming Language :: Python :: 3
License-File: LICENSE.md
Requires-Dist: djangoldp (==2.1.43)
Requires-Dist: djangoldp-account (==2.3.18)
Requires-Dist: djangoldp-uploader (==2.1.2)
Requires-Dist: beautifulsoup4
Requires-Dist: requests
Requires-Dist: selenium (==3.14.1)
Requires-Dist: webdriver-manager
Provides-Extra: dev
Requires-Dist: requests-mock ; extra == 'dev'
Provides-Extra: include_package_data
Requires-Dist: True ; extra == 'include_package_data'
